kudaflib/__init__.py
kudaflib/auth.py
kudaflib/config/__init__.py
kudaflib/config/config_example.yaml
kudaflib/config/settings.py
kudaflib/logic/__init__.py
kudaflib/logic/auth_cc_flow.py
kudaflib/logic/connect.py
kudaflib/logic/dcat_process.py
kudaflib/logic/exceptions.py
kudaflib/logic/models.py
kudaflib/logic/process.py
kudaflib/logic/unit_type_process.py
kudaflib/logic/utils.py
kudaflib/logic/variable_process.py
kudaflib/main.py
kudaflib/metadata/__init__.py
kudaflib/metadata/temporal_attributes.py
kudaflib/metadata/unit_type_variables/FYLKE.json
kudaflib/metadata/unit_type_variables/FYLKESKOMMUNE.json
kudaflib/metadata/unit_type_variables/KOMMUNE.json
kudaflib/metadata/unit_type_variables/ORGANISASJON.json
kudaflib/metadata/unit_type_variables/PERSON.json
kudaflib/metadata/unit_type_variables/__init__.py
kudaflib/schemas/__init__.py
kudaflib/schemas/dcat.py
kudaflib/schemas/helpers.py
kudaflib/schemas/variable.py
kudaflib/static/kdst_download.png
kudaflib-0.3.3.dist-info/LICENSE.md
kudaflib-0.3.3.dist-info/METADATA
kudaflib-0.3.3.dist-info/WHEEL
kudaflib-0.3.3.dist-info/entry_points.txt
kudaflib-0.3.3.dist-info/RECORD
