Metadata-Version: 2.3
Name: kudaflib
Version: 0.3.3
Summary: This Python library contains KUDAF metadata schema definitions and logic that is common and applicable to other KUDAF Python packages
License: MIT
Author: Daniel Díguele, Senioringeniør, Sikt - Kunnskapssektorens tjenesteleverandør 
Author-email: daniel.diguele@sikt.no
Maintainer: Daniel Díguele, Senioringeniør, Sikt - Kunnskapssektorens tjenesteleverandør 
Maintainer-email: daniel.diguele@sikt.no
Requires-Python: >=3.8,<3.11
Classifier: License :: OSI Approved :: MIT License
Classifier: Operating System :: OS Independent
Classifier: Programming Language :: Python :: 3
Classifier: Programming Language :: Python :: 3.8
Classifier: Programming Language :: Python :: 3.9
Classifier: Programming Language :: Python :: 3.10
Classifier: Topic :: Utilities
Requires-Dist: datacatalogtordf (>=3.0.0)
Requires-Dist: httpx (>=0.28.0)
Requires-Dist: pydantic (>=2.10)
Requires-Dist: pydantic-settings (>=2.6.1)
Requires-Dist: python-dotenv (>=1.0.1)
Requires-Dist: rich (>=13.7.1)
Requires-Dist: ruamel-yaml (>=0.18.5)
Requires-Dist: typer (>=0.15.1,<0.16.0)
Project-URL: Bug Tracker, https://gitlab.sikt.no/kudaf/kudaflib/-/issues
Project-URL: Homepage, https://gitlab.sikt.no/kudaf/kudaflib
Project-URL: Repository, https://gitlab.sikt.no/kudaf/kudaflib
Project-URL: readme, https://gitlab.sikt.no/kudaf/kudaflib/-/blob/main/README.md
